{
  "buildCommand" : {
    "command" : "build",
    "skipDependencies" : false,
    "style" : "buildAndRun"
  },
  "configuredTargets" : [
    {
      "guid" : "3b05f5f30e04711eb26e9a99ceae1e272778e1228159ee35b161f3887acf0587"
    }
  ],
  "containerPath" : "/Users/jackson/Projects/Parakeet/ios/ParakeetVoice.xcodeproj",
  "continueBuildingAfterErrors" : false,
  "dependencyScope" : "workspace",
  "enableIndexBuildArena" : false,
  "hideShellScriptEnvironment" : false,
  "parameters" : {
    "action" : "build",
    "configurationName" : "Debug",
    "overrides" : {
      "commandLine" : {
        "table" : {
          "SDKROOT" : "iphonesimulator18.2"
        }
      },
      "synthesized" : {
        "table" : {
          "ACTION" : "build",
          "ENABLE_PREVIEWS" : "NO",
          "ENABLE_XOJIT_PREVIEWS" : "NO"
        }
      }
    }
  },
  "showNonLoggedProgress" : true,
  "useDryRun" : false,
  "useImplicitDependencies" : false,
  "useLegacyBuildLocations" : false,
  "useParallelTargets" : true
}